pypm/__init__.py
pypm/__main__.py
pypm/constants.py
pypm/manager.py
pypm/monit.py
pypm/process.py
pypm/pypm.py
pypm/units.py
pypm/visual.py
python_pm-0.0.4.dist-info/LICENSE
python_pm-0.0.4.dist-info/METADATA
python_pm-0.0.4.dist-info/WHEEL
python_pm-0.0.4.dist-info/top_level.txt
python_pm-0.0.4.dist-info/RECORD
