Metadata-Version: 2.1
Name: python-pm
Version: 0.0.4
Summary: A simple, python-based process manager
Home-page: https://github.com/ArmindoFlores/pypm
Author: Francisco Rodrigues
Author-email: francisco.rodrigues0908@gmail.com
License: UNKNOWN
Platform: UNKNOWN
Classifier: Programming Language :: Python :: 3
Classifier: License :: OSI Approved :: MIT License
Classifier: Operating System :: OS Independent
Requires-Dist: psutil (>=5.7.2)
Requires-Dist: termtables (>=0.2.2)
Requires-Dist: matplotlib (>=3.2.1)
Requires-Dist: colorama (>=0.4.3)
